pynet_annek/__init__.py
pynet_annek/cli.py
pynet_annek/sqlitenet.py
pynet_annek-0.5.4.dist-info/entry_points.txt
pynet_annek-0.5.4.dist-info/LICENSE
pynet_annek-0.5.4.dist-info/WHEEL
pynet_annek-0.5.4.dist-info/METADATA
pynet_annek-0.5.4.dist-info/RECORD
