Metadata-Version: 2.1
Name: pynet-annek
Version: 0.5.4
Summary: A cli for managing network switches
License: MIT
Author: Michael MacKenna
Author-email: mpmackenna@gmail.com
Requires-Python: >=3.8,<4.0
Classifier: License :: OSI Approved :: MIT License
Classifier: Programming Language :: Python :: 3
Classifier: Programming Language :: Python :: 3.8
Requires-Dist: click (>=7.0,<8.0)
Requires-Dist: netmiko (>=2.4,<3.0)
Requires-Dist: termcolor (>=1.1,<2.0)
